helloledger/__init__.py
helloledger/client.py
helloledger/exceptions.py
helloledger/version.py
helloledger/resources/__init__.py
helloledger/resources/companies.py
helloledger/resources/transactions.py
helloledger-0.1.1.dist-info/licenses/LICENSE
helloledger-0.1.1.dist-info/METADATA
helloledger-0.1.1.dist-info/WHEEL
helloledger-0.1.1.dist-info/top_level.txt
helloledger-0.1.1.dist-info/RECORD
