Metadata-Version: 2.4
Name: helloledger
Version: 0.1.1
Summary: Official Python SDK for HelloLedger API
Author-email: HelloLedger <support@helloledger.ai>
License-Expression: MIT
Project-URL: Homepage, https://pypi.org/project/helloledger/
Project-URL: Documentation, https://github.com/helloledger/helloledger-python#readme
Project-URL: Repository, https://github.com/helloledger/helloledger-python
Project-URL: Issues, https://github.com/helloledger/helloledger-python/issues
Keywords: helloledger,accounting,finance,api,sdk
Classifier: Development Status :: 3 - Alpha
Classifier: Intended Audience :: Developers
Classifier: Programming Language :: Python :: 3
Classifier: Programming Language :: Python :: 3.8
Classifier: Programming Language :: Python :: 3.9
Classifier: Programming Language :: Python :: 3.10
Classifier: Programming Language :: Python :: 3.11
Classifier: Programming Language :: Python :: 3.12
Classifier: Topic :: Software Development :: Libraries :: Python Modules
Classifier: Topic :: Office/Business :: Financial :: Accounting
Requires-Python: >=3.8
License-File: LICENSE
Requires-Dist: httpx>=0.24.0
Provides-Extra: dev
Requires-Dist: pytest>=7.0.0; extra == "dev"
Requires-Dist: pytest-cov>=4.0.0; extra == "dev"
Requires-Dist: black>=23.0.0; extra == "dev"
Requires-Dist: mypy>=1.0.0; extra == "dev"
Requires-Dist: ruff>=0.1.0; extra == "dev"
Dynamic: license-file
